pyutmodelv2/PyutActor.py
pyutmodelv2/PyutClass.py
pyutmodelv2/PyutClassCommon.py
pyutmodelv2/PyutField.py
pyutmodelv2/PyutInterface.py
pyutmodelv2/PyutLink.py
pyutmodelv2/PyutLinkedObject.py
pyutmodelv2/PyutMethod.py
pyutmodelv2/PyutModelTypes.py
pyutmodelv2/PyutModifier.py
pyutmodelv2/PyutNote.py
pyutmodelv2/PyutObject.py
pyutmodelv2/PyutParameter.py
pyutmodelv2/PyutSDInstance.py
pyutmodelv2/PyutSDMessage.py
pyutmodelv2/PyutText.py
pyutmodelv2/PyutType.py
pyutmodelv2/PyutUseCase.py
pyutmodelv2/__init__.py
pyutmodelv2/_version.py
pyutmodelv2/py.typed
pyutmodelv2/enumerations/PyutDisplayMethods.py
pyutmodelv2/enumerations/PyutDisplayParameters.py
pyutmodelv2/enumerations/PyutLinkType.py
pyutmodelv2/enumerations/PyutStereotype.py
pyutmodelv2/enumerations/PyutVisibility.py
pyutmodelv2/enumerations/__init__.py
pyutmodelv2/enumerations/py.typed
pyutmodelv2-2.2.6.dist-info/licenses/LICENSE
pyutmodelv2-2.2.6.dist-info/METADATA
pyutmodelv2-2.2.6.dist-info/WHEEL
pyutmodelv2-2.2.6.dist-info/top_level.txt
pyutmodelv2-2.2.6.dist-info/RECORD
